Xv6RiscvBookZhongwenban/README.md
Xv6RiscvBookZhongwenban/__init__.py
Xv6RiscvBookZhongwenban/__main__.py
Xv6RiscvBookZhongwenban/file.epub
Xv6RiscvBookZhongwenban/index.html
Xv6RiscvBookZhongwenban/css/__init__.py
Xv6RiscvBookZhongwenban/css/annotations.css
Xv6RiscvBookZhongwenban/css/main.css
Xv6RiscvBookZhongwenban/css/normalize.css
Xv6RiscvBookZhongwenban/css/popup.css
Xv6RiscvBookZhongwenban/font/__init__.py
Xv6RiscvBookZhongwenban/font/fontello.eot
Xv6RiscvBookZhongwenban/font/fontello.svg
Xv6RiscvBookZhongwenban/font/fontello.ttf
Xv6RiscvBookZhongwenban/font/fontello.woff
Xv6RiscvBookZhongwenban/img/__init__.py
Xv6RiscvBookZhongwenban/img/annotator-glyph-sprite.png
Xv6RiscvBookZhongwenban/img/annotator-icon-sprite.png
Xv6RiscvBookZhongwenban/img/apple-touch-icon.png
Xv6RiscvBookZhongwenban/img/cancelfullscreen.png
Xv6RiscvBookZhongwenban/img/close.png
Xv6RiscvBookZhongwenban/img/fullscreen.png
Xv6RiscvBookZhongwenban/img/loader.gif
Xv6RiscvBookZhongwenban/img/menu-icon.png
Xv6RiscvBookZhongwenban/img/save.png
Xv6RiscvBookZhongwenban/img/saved.png
Xv6RiscvBookZhongwenban/img/settings-s.png
Xv6RiscvBookZhongwenban/img/settings.png
Xv6RiscvBookZhongwenban/img/star.png
Xv6RiscvBookZhongwenban/js/__init__.py
Xv6RiscvBookZhongwenban/js/epub.js
Xv6RiscvBookZhongwenban/js/epub.min.js
Xv6RiscvBookZhongwenban/js/epub.min.map
Xv6RiscvBookZhongwenban/js/hooks.min.js
Xv6RiscvBookZhongwenban/js/hooks.min.map
Xv6RiscvBookZhongwenban/js/reader.js
Xv6RiscvBookZhongwenban/js/reader.js.map
Xv6RiscvBookZhongwenban/js/reader.min.js
Xv6RiscvBookZhongwenban/js/reader.min.map
Xv6RiscvBookZhongwenban/js/hooks/__init__.py
Xv6RiscvBookZhongwenban/js/hooks/extensions/__init__.py
Xv6RiscvBookZhongwenban/js/hooks/extensions/highlight.js
Xv6RiscvBookZhongwenban/js/libs/__init__.py
Xv6RiscvBookZhongwenban/js/libs/jquery.min.js
Xv6RiscvBookZhongwenban/js/libs/localforage.min.js
Xv6RiscvBookZhongwenban/js/libs/screenfull.js
Xv6RiscvBookZhongwenban/js/libs/screenfull.min.js
xv6_riscv_book_zhongwenban-2024.3.5.0.dist-info/METADATA
xv6_riscv_book_zhongwenban-2024.3.5.0.dist-info/WHEEL
xv6_riscv_book_zhongwenban-2024.3.5.0.dist-info/entry_points.txt
xv6_riscv_book_zhongwenban-2024.3.5.0.dist-info/top_level.txt
xv6_riscv_book_zhongwenban-2024.3.5.0.dist-info/RECORD
